dyntripy/__init__.py
dyntripy/plot_utils.py
dyntripy/triggering.py
dyntripy/utils.py
dyntripy/hifi/AssociateBackgroundPIR.py
dyntripy/hifi/ConfidenceLevel.py
dyntripy/hifi/HighPIRatio.py
dyntripy/hifi/PIdatabase.py
dyntripy/hifi/__init__.py
dyntripy-3.2.4.dist-info/LICENSE
dyntripy-3.2.4.dist-info/METADATA
dyntripy-3.2.4.dist-info/WHEEL
dyntripy-3.2.4.dist-info/top_level.txt
dyntripy-3.2.4.dist-info/RECORD
