Metadata-Version: 2.1
Name: dyntripy
Version: 3.2.4
Summary: A package for detecting dynamic triggering automatically
Home-page: https://github.com/yunndlalala/dynamic_earthquake_triggering
Author: Naidan YUN
Author-email: yunnaidan@gmail.com
License: UNKNOWN
Platform: UNKNOWN
Classifier: Programming Language :: Python :: 3
Classifier: License :: OSI Approved :: MIT License
Classifier: Operating System :: OS Independent
Requires-Python: >=3.6.8
Requires-Dist: obspy (>=1.1.0)
Requires-Dist: matplotlib (>=3.1.2)
Requires-Dist: pandas (>=0.24.2)
Requires-Dist: scipy (>=1.1.0)
Requires-Dist: numpy (>=1.16.3)
